{
  "usuariosPremium": [
    {
      "contrasenia": "maestro",
      "nombreUsuario": "frannquir",
      "email": "franciscoquirogax@gmail.com",
      "identificador": "231f034f-147e-4a97-a288-77f050eac587",
      "activo": true
    },
    {
      "contrasenia": "discord",
      "nombreUsuario": "juliramos",
      "email": "julietaramos@gmail.com",
      "identificador": "699f8552-5ac6-4211-9ff2-a171147d6469",
      "activo": true
    }
  ],
  "usuariosFree": [{
    "contrasenia": "doaobini",
    "nombreUsuario": "ricardomati",
    "email": "matiasricardenez@gmail.com",
    "identificador": "27fd0f9d-637b-4e54-ba12-bb669ca3cb7a",
    "activo": true
  }]
}